quica/__init__.py
quica/quica.py
quica/dataset/__init__.py
quica/dataset/dataset.py
quica/internal/__init__.py
quica/internal/measures.py
quica/measures/__init__.py
quica/measures/irr.py
quica-0.2.5.dist-info/AUTHORS.rst
quica-0.2.5.dist-info/LICENSE
quica-0.2.5.dist-info/METADATA
quica-0.2.5.dist-info/WHEEL
quica-0.2.5.dist-info/top_level.txt
quica-0.2.5.dist-info/RECORD
