Metadata-Version: 2.1
Name: quica
Version: 0.2.5
Summary: Quick Inter Coder Agreement in Python
Home-page: https://github.com/vinid/quica
Author: Federico Bianchi
Author-email: f.bianchi@unibocconi.it
License: MIT license
Keywords: quica
Platform: UNKNOWN
Classifier: Development Status :: 2 - Pre-Alpha
Classifier: Intended Audience :: Developers
Classifier: License :: OSI Approved :: MIT License
Classifier: Natural Language :: English
Classifier: Programming Language :: Python :: 3
Classifier: Programming Language :: Python :: 3.5
Classifier: Programming Language :: Python :: 3.6
Classifier: Programming Language :: Python :: 3.7
Classifier: Programming Language :: Python :: 3.8
Requires-Python: >=3.5
Requires-Dist: krippendorff
Requires-Dist: sklearn
Requires-Dist: nltk
Requires-Dist: pandas
